tftokenizers/__init__.py
tftokenizers/database.py
tftokenizers/detect.py
tftokenizers/download.py
tftokenizers/file.py
tftokenizers/main.py
tftokenizers/model.py
tftokenizers/tokenizer.py
tftokenizers/types.py
tftokenizers/utils.py
tftokenizers-0.1.8.dist-info/entry_points.txt
tftokenizers-0.1.8.dist-info/LICENSE
tftokenizers-0.1.8.dist-info/WHEEL
tftokenizers-0.1.8.dist-info/METADATA
tftokenizers-0.1.8.dist-info/RECORD
