Metadata-Version: 2.1
Name: tftokenizers
Version: 0.1.8
Summary: Use Huggingface Transformer and Tokenizers as Tensorflow Reusable SavedModels.
Home-page: https://github.com/Hugging-Face-Supporter/tftokenizers
License: Apache-2.0
Keywords: huggingface,transformers,tokenizers,tensorflow,text
Author: MarkusSagen
Author-email: markus.john.sagen@gmail.com
Requires-Python: >=3.7,<3.10
Classifier: License :: OSI Approved :: Apache Software License
Classifier: Programming Language :: Python :: 3
Classifier: Programming Language :: Python :: 3.7
Classifier: Programming Language :: Python :: 3.8
Classifier: Programming Language :: Python :: 3.9
Requires-Dist: pydantic (>=1.6.0,<2.0.0)
Requires-Dist: rich[jupyter] (>=10.12.0,<11.0.0)
Requires-Dist: sentencepiece (>=0.1.92,<0.2.0)
Requires-Dist: tensorflow (>=2.5.0,<3.0.0)
Requires-Dist: tensorflow-text (>=2.5.0,<3.0.0)
Requires-Dist: tf-sentencepiece (>=0.1.92,<0.2.0)
Requires-Dist: torch (>=1.6.0,<2.0.0)
Requires-Dist: transformers (>=4.0.1,<5.0.0)
Project-URL: Repository, https://github.com/Hugging-Face-Supporter/tftokenizers
